{
  "cookies": [
    {
      "name": "slim_session",
      "value": "3EnFZN5IUDOaRmrZibtVE5YguNuTO7tu7E5i0Y1S",
      "domain": "qacart.com",
      "path": "/",
      "expires": 1740640821.879857,
      "httpOnly": true,
      "secure": true,
      "sameSite": "None"
    },
    {
      "name": "test_cookie",
      "value": "CheckForPermission",
      "domain": ".doubleclick.net",
      "path": "/",
      "expires": 1740425722.007568,
      "httpOnly": true,
      "secure": true,
      "sameSite": "None"
    }
  ],
  "origins": [
    {
      "origin": "https://qacart.com",
      "localStorage": [
        {
          "name": "anonymous_token",
          "value": "{\"token\":\"67bcc6749e38df2fc817anon\",\"lastAccessed\":1740424821763}"
        }
      ]
    },
    {
      "origin": "https://www.google.com",
      "localStorage": [
        {
          "name": "rc::a",
          "value": "MXBtbmVuZWdrMzF2NA=="
        }
      ]
    }
  ]
}